libname/__init__.py
libname/hello.py
jlhello-2.0.dist-info/METADATA
jlhello-2.0.dist-info/WHEEL
jlhello-2.0.dist-info/top_level.txt
jlhello-2.0.dist-info/RECORD
