Metadata-Version: 2.1
Name: jlhello
Version: 2.0
Summary: First package of Jalon L
Author: Jalon Liang
Author-email: jalonliang@hello.com
Keywords: newbies,python,package,distribution
Requires-Dist: nothing
